clash_tools/__init__.py
clash_tools/clash_tools/Country.mmdb
clash_tools/clash_tools/__init__.py
clash_tools/clash_tools/clash
clash_tools/clash_tools/clash_docker.py
clash_tools/clash_tools/clash_proxy.py
clash_tools/clash_tools/clash_serve.py
clash_tools/clash_tools/config.py
clash_tools/clash_tools/config.yaml
clash_tools/wg_docker/__init__.py
clash_tools/wg_docker/cli.py
clash_tools/wg_docker/config.py
clash_tools/wg_docker/models.py
clash_tools/wg_docker/utils.py
clash_tools/wg_docker/templates/client_compose.yml.j2
clash_tools/wg_docker/templates/client_wg0.conf.j2
clash_tools/wg_docker/templates/server_compose.yml.j2
clash_tools/wg_docker/templates/server_config.yml
clash_tools/wg_docker/templates/server_wg0.conf.j2
clash_tools-3.3.1.dist-info/licenses/LICENSE
clash_tools-3.3.1.dist-info/METADATA
clash_tools-3.3.1.dist-info/WHEEL
clash_tools-3.3.1.dist-info/entry_points.txt
clash_tools-3.3.1.dist-info/top_level.txt
clash_tools-3.3.1.dist-info/RECORD
