Metadata-Version: 2.4
Name: clash_tools
Version: 3.3.1
Summary: clash_tools is a comprehensive collection of utilities for managing Clash proxy configurations and services.
Author-email: sleeping-in-bed <nyanyanyaworld@gmail.com>
Classifier: Programming Language :: Python
Classifier: Programming Language :: Python :: 3 :: Only
Classifier: Programming Language :: Python :: 3.10
Classifier: Programming Language :: Python :: 3.11
Classifier: Programming Language :: Python :: 3.12
Classifier: Programming Language :: Python :: 3.13
Classifier: Operating System :: OS Independent
Requires-Python: >=3.10
License-File: LICENSE
Requires-Dist: click
Requires-Dist: PyYAML
Requires-Dist: types-pyyaml
Requires-Dist: jinja2
Requires-Dist: pydantic
Requires-Dist: typer
Requires-Dist: pytest
Dynamic: license-file
